LICENSE
MANIFEST.in
README.rst
requirements-dev.txt
requirements.txt
setup.cfg
setup.py
iec870ree/__init__.py
iec870ree/app_asdu.py
iec870ree/base_asdu.py
iec870ree/events.py
iec870ree/ip.py
iec870ree/modem.py
iec870ree/protocol.py
iec870ree.egg-info/PKG-INFO
iec870ree.egg-info/SOURCES.txt
iec870ree.egg-info/dependency_links.txt
iec870ree.egg-info/requires.txt
iec870ree.egg-info/top_level.txt
tests/test_app_asdu.py
tests/test_base_asdu.py
tests/test_ip.py
tests/test_modem.py
tests/test_protocol.py