Metadata-Version: 2.1
Name: iec870ree
Version: 0.14.1
Summary: Library to connect and query information about electricmeters following REE protocol.
Home-page: https://github.com/gisce/iec870ree
Author: GISCE-TI, S.L.
Author-email: devel@gisce.net
License: GNU Affero General Public License v3
Classifier: Development Status :: 4 - Beta
Classifier: License :: OSI Approved :: GNU Affero General Public License v3
Classifier: Programming Language :: Python :: 2.7
Classifier: Programming Language :: Python :: 3.5
Classifier: Topic :: Utilities
License-File: LICENSE
